LICENSE.txt
MANIFEST.in
setup.py
thinkgear/__init__.py
thinkgear/thinkgear.py
thinkgear.egg-info/PKG-INFO
thinkgear.egg-info/SOURCES.txt
thinkgear.egg-info/dependency_links.txt
thinkgear.egg-info/top_level.txt