Metadata-Version: 1.0
Name: thinkgear
Version: 0.2
Summary: thinkgear parses the ThinkGear protocol used by NeuroSky MindSet devices
Home-page: UNKNOWN
Author: Kai Groner
Author-email: kai@gronr.com
License: BSD
Platform: UNKNOWN
Classifier: Development Status :: 3 - Alpha
Classifier: Intended Audience :: Developers
Classifier: Programming Language :: Python
Classifier: Operating System :: OS Independent
Classifier: License :: OSI Approved :: BSD License
Classifier: Topic :: Scientific/Engineering :: Human Machine Interfaces
